wdl_parsers/__init__.py
wdl_parsers/development/WdlLexer.py
wdl_parsers/development/WdlParser.py
wdl_parsers/development/WdlParserListener.py
wdl_parsers/development/WdlParserVisitor.py
wdl_parsers/development/__init__.py
wdl_parsers/draft_2/__init__.py
wdl_parsers/draft_2/wdl_parser.py
wdl_parsers/v1_0/WdlV1Lexer.py
wdl_parsers/v1_0/WdlV1Parser.py
wdl_parsers/v1_0/WdlV1ParserListener.py
wdl_parsers/v1_0/WdlV1ParserVisitor.py
wdl_parsers/v1_0/__init__.py
wdl_parsers/v1_1/WdlV1_1Lexer.py
wdl_parsers/v1_1/WdlV1_1Parser.py
wdl_parsers/v1_1/WdlV1_1ParserListener.py
wdl_parsers/v1_1/WdlV1_1ParserVisitor.py
wdl_parsers/v1_1/__init__.py
wdl_parsers-0.2.0.dist-info/LICENSE
wdl_parsers-0.2.0.dist-info/METADATA
wdl_parsers-0.2.0.dist-info/WHEEL
wdl_parsers-0.2.0.dist-info/top_level.txt
wdl_parsers-0.2.0.dist-info/RECORD
